proto_formatter/__init__.py
proto_formatter/comment.py
proto_formatter/constant.py
proto_formatter/detector.py
proto_formatter/import_parser.py
proto_formatter/label.py
proto_formatter/object_parser.py
proto_formatter/option_parser.py
proto_formatter/package_parser.py
proto_formatter/parser.py
proto_formatter/proto_structures.py
proto_formatter/protobuf.py
proto_formatter/syntax_parser.py
proto_formatter/util.py
proto_formatter/utils.py
proto_formatter/value_types.py
proto_formatter/wrap_enum.py
proto_formatter-0.1.3.dist-info/LICENSE
proto_formatter-0.1.3.dist-info/METADATA
proto_formatter-0.1.3.dist-info/WHEEL
proto_formatter-0.1.3.dist-info/top_level.txt
proto_formatter-0.1.3.dist-info/RECORD
